MarkMyImage/__init__.py
MarkMyImage-0.1.8.dist-info/METADATA
MarkMyImage-0.1.8.dist-info/WHEEL
MarkMyImage-0.1.8.dist-info/entry_points.txt
MarkMyImage-0.1.8.dist-info/top_level.txt
MarkMyImage-0.1.8.dist-info/RECORD
